CHANGES.txt
COPYRIGHT.txt
LICENSE.txt
README.txt
bootstrap.py
buildout.cfg
setup.py
src/z3c/__init__.py
src/z3c.objectpolicy.egg-info/PKG-INFO
src/z3c.objectpolicy.egg-info/SOURCES.txt
src/z3c.objectpolicy.egg-info/dependency_links.txt
src/z3c.objectpolicy.egg-info/namespace_packages.txt
src/z3c.objectpolicy.egg-info/not-zip-safe
src/z3c.objectpolicy.egg-info/requires.txt
src/z3c.objectpolicy.egg-info/top_level.txt
src/z3c/objectpolicy/README.txt
src/z3c/objectpolicy/__init__.py
src/z3c/objectpolicy/configure.zcml
src/z3c/objectpolicy/highlevel.txt
src/z3c/objectpolicy/interfaces.py
src/z3c/objectpolicy/lowlevel.txt
src/z3c/objectpolicy/objectpolicy.py
src/z3c/objectpolicy/tests.py
src/z3c/objectpolicy/z3c.objectpolicy-configure.zcml
src/z3c/objectpolicy/zopepolicy_copy.txt
src/z3c/objectpolicy/zopepolicy_objectpolicy.txt