Metadata-Version: 1.0
Name: z3c.objectpolicy
Version: 0.1
Summary: objectpolicy for Zope3
Home-page: http://cheeseshop.python.org/pypi/z3c.objectpolicy
Author: Zope Foundation and Contributors
Author-email: zope-dev@zope.org
License: ZPL 2.1
Keywords: zope3 z3c objectpolicy
Platform: UNKNOWN
Classifier: Development Status :: 4 - Beta
Classifier: Environment :: Web Environment
Classifier: Intended Audience :: Developers
Classifier: License :: OSI Approved :: Zope Public License
Classifier: Programming Language :: Python
Classifier: Natural Language :: English
Classifier: Operating System :: OS Independent
Classifier: Topic :: Internet :: WWW/HTTP
Classifier: Framework :: Zope3
